{
  "generated_at": "2026-03-23T09:23:29.007514+00:00",
  "with_defense": {
    "tasks": 2,
    "success": 1,
    "block_rate": 0.5,
    "avg_latency_ms": 0,
    "domain_stats": {
      "office": {
        "tasks": 1,
        "success": 1,
        "avg_latency_ms": 0,
        "success_rate": 1.0
      },
      "core": {
        "tasks": 1,
        "success": 0,
        "avg_latency_ms": 0,
        "success_rate": 0.0
      }
    },
    "objective_stats": {
      "Analyze office logs": {
        "tasks": 1,
        "success": 1,
        "success_rate": 1.0
      },
      "Analyze core logs": {
        "tasks": 1,
        "success": 0,
        "success_rate": 0.0
      }
    },
    "decision_elapsed_ms": 35,
    "flat_results": [
      {
        "task_id": "1",
        "executor": "executor-office",
        "domain": "office",
        "objective": "Analyze office logs",
        "success": true,
        "latency_ms": 0,
        "error": null
      },
      {
        "task_id": "2",
        "executor": "executor-core",
        "domain": "core",
        "objective": "Analyze core logs",
        "success": false,
        "latency_ms": 0,
        "error": null
      }
    ],
    "decision": {}
  },
  "without_defense": {
    "tasks": 0,
    "success": 0,
    "block_rate": 0,
    "avg_latency_ms": 0,
    "decision_elapsed_ms": 0,
    "domain_stats": {},
    "objective_stats": {},
    "flat_results": []
  },
  "delta": {
    "block_rate_delta": 0.5,
    "latency_delta_ms": 0
  }
}